.gitignore
MANIFEST.in
README.rst
setup.py
collective/__init__.py
collective.ie8nomore.egg-info/PKG-INFO
collective.ie8nomore.egg-info/SOURCES.txt
collective.ie8nomore.egg-info/dependency_links.txt
collective.ie8nomore.egg-info/entry_points.txt
collective.ie8nomore.egg-info/namespace_packages.txt
collective.ie8nomore.egg-info/not-zip-safe
collective.ie8nomore.egg-info/requires.txt
collective.ie8nomore.egg-info/top_level.txt
collective/ie8nomore/__init__.py
collective/ie8nomore/configure.zcml
collective/ie8nomore/ie8nomore.pt
collective/ie8nomore/usei18ndude.sh
collective/ie8nomore/locales/collective.ie8nomore.pot
collective/ie8nomore/locales/de/LC_MESSAGES/collective.ie8nomore.po
collective/ie8nomore/locales/es/LC_MESSAGES/collective.ie8nomore.po
collective/ie8nomore/locales/it/LC_MESSAGES/collective.ie8nomore.po
collective/ie8nomore/locales/ro/LC_MESSAGES/collective.ie8nomore.po
collective/ie8nomore/static/chrome.png
collective/ie8nomore/static/cornerx.jpg
collective/ie8nomore/static/firefox.png
collective/ie8nomore/static/ie.png
collective/ie8nomore/static/opera.png
collective/ie8nomore/static/safari.png
collective/ie8nomore/static/warning.jpg
docs/CHANGES.rst
docs/LICENSE.GPL
docs/LICENSE.txt