Metadata-Version: 1.1
Name: collective.ie8nomore
Version: 0.6
Summary: Plone viewlet to prompt users to upgrade to a better web browser.
Home-page: https://github.com/collective/collective.ie8nomore
Author: Noe Nieto
Author-email: nnieto@noenieto.com
License: GPL
Keywords: plone internet explorer
Platform: UNKNOWN
Classifier: Development Status :: 4 - Beta
Classifier: Framework :: Plone
Classifier: Framework :: Plone :: 4.1
Classifier: Programming Language :: Python
Classifier: Topic :: Software Development :: Libraries :: Python Modules
Classifier: License :: OSI Approved :: GNU General Public License (GPL)
Classifier: Natural Language :: English
Classifier: Natural Language :: Spanish
